LICENSE
MANIFEST.in
README.md
setup.cfg
setup.py
dbf_reader/__init__.py
dbf_reader/definitions.py
dbf_reader/reader.py
dbf_reader/renderers.py
dbf_reader.egg-info/PKG-INFO
dbf_reader.egg-info/SOURCES.txt
dbf_reader.egg-info/dependency_links.txt
dbf_reader.egg-info/top_level.txt