Metadata-Version: 1.1
Name: dbf-reader
Version: 0.1.7
Summary: Utils classes to read DBF files, specially DATASUS compressed DBF files
Home-page: https://github.com/lais-huol/dbf_reader
Author: Kelson da Costa Medeiros
Author-email: kelson.medeiros@lais.huol.ufrn.br
License: MIT
Download-URL: https://github.com/lais-huol/dbf_reader/releases/tag/0.1.7
Keywords: DBF,DBC,reader,datasus
Platform: UNKNOWN
Classifier: Programming Language :: Python :: 3
Classifier: License :: OSI Approved :: MIT License
Classifier: Operating System :: OS Independent
